Workbook

Sheet Припущення
A1: TouchRetouch — модель воронки та ROAS (Apple Search Ads)
A2: Помаранчеві клітинки — редаговані вхідні. Сині — розраховані. Дохід рахується на базі ARPPU за перший рік.
A4: ОСНОВНІ ПРИПУЩЕННЯ ВОРОНКИ (редагуй ці)
A5: Показник | B5: Значення | C5: Од. | D5: Примітка / джерело
A6: Інстал → Тріал | B6: 0.15 | C6: % | D6: Дано (платна воронка)
A7: Тріал → Оплата | B7: 0.2 | C7: % | D7: Дано (платна воронка)
A8: ARPPU (1-й рік, без комісії Apple) | B8: 22.2 | C8: $ | D8: Дано
A9: Визнання доходу на D30 (частка річного) | B9: 0.45 | C9: % | D9: ЛИШЕ ДОВІДКА (не в гейті) — взяти реальну криву D30/рік з RevenueCat
A10: Мін. ROAS для масштабування (D30) | B10: 1.25 | C10: x | D10: Вимога з завдання
A12: ПОХІДНА ЮНІТ-ЕКОНОМІКА (розрахунок)
A13: Платників на інстал | B13: =$B$6*$B$7 | D13: тріал% × оплата%
A14: Дохід на інстал (рік) | B14: =$B$13*$B$8 | D14: платників/інстал × ARPPU
A15: Беззбитковий CPI (ROAS 100%) | B15: =$B$14 | D15: дорівнює доходу на інстал
A16: Цільовий CPI для мін. ROAS | B16: =$B$14/$B$10 | D16: дохід/інстал ÷ мін. ROAS
A18: ГОЛОВНЕ: уся задача = опустити блендовий CPI до ≤ цільового і втримати, подвоюючи витрати.

Sheet Модель
A1: Витрати → Тапи → Інстали → Тріали → Платники → Дохід → ROAS
A2: Помаранчеве — редаговані драйвери. Решта — живі формули. Логіка: спершу банкуємо ефективність (M1), потім масштабуємо в запас.
A4: Фаза / місяць | B4: Витрати ($) | C4: Блендовий CPT ($) | D4: TTR | E4: CR тап→інстал | F4: CPI ($) | G4: Тапи | H4: Інстали | I4: Тріали | J4: Платники | K4: Дохід ($) | L4: D30 кеш | M4: ROAS (гейт) | N4: D30 ROAS | O4: Гейт?
A5: M0 — Базовий (зараз) | B5: 35000 | C5: 0.2564 | D5: 0.07 | E5: 0.385 | F5: =C5/E5 | G5: =B5/C5 | H5: =G5*E5 | I5: =H5*Припущення!$B$6 | J5: =I5*Припущення!$B$7 | K5: =J5*Припущення!$B$8 | L5: =K5*Припущення!$B$9 | M5: =K5/B5 | N5: =L5/B5 | O5: =IF(M5>=Припущення!$B$10,"ТАК","НІ")
A6: M1 — Банк ефективності | B6: 35000 | C6: 0.224 | D6: 0.075 | E6: 0.4 | F6: =C6/E6 | G6: =B6/C6 | H6: =G6*E6 | I6: =H6*Припущення!$B$6 | J6: =I6*Припущення!$B$7 | K6: =J6*Припущення!$B$8 | L6: =K6*Припущення!$B$9 | M6: =K6/B6 | N6: =L6/B6 | O6: =IF(M6>=Припущення!$B$10,"ТАК","НІ")
A7: M2 — Гейт пройдено | B7: 40000 | C7: 0.223 | D7: 0.078 | E7: 0.42 | F7: =C7/E7 | G7: =B7/C7 | H7: =G7*E7 | I7: =H7*Припущення!$B$6 | J7: =I7*Припущення!$B$7 | K7: =J7*Припущення!$B$8 | L7: =K7*Припущення!$B$9 | M7: =K7/B7 | N7: =L7/B7 | O7: =IF(M7>=Припущення!$B$10,"ТАК","НІ")
A8: M3 — Скейл понад гейт | B8: 55000 | C8: 0.2323 | D8: 0.08 | E8: 0.44 | F8: =C8/E8 | G8: =B8/C8 | H8: =G8*E8 | I8: =H8*Припущення!$B$6 | J8: =I8*Припущення!$B$7 | K8: =J8*Припущення!$B$8 | L8: =K8*Припущення!$B$9 | M8: =K8/B8 | N8: =L8/B8 | O8: =IF(M8>=Припущення!$B$10,"ТАК","НІ")
A9: Q2 — Ціль | B9: 70000 | C9: 0.2363 | D9: 0.082 | E9: 0.45 | F9: =C9/E9 | G9: =B9/C9 | H9: =G9*E9 | I9: =H9*Припущення!$B$6 | J9: =I9*Припущення!$B$7 | K9: =J9*Припущення!$B$8 | L9: =K9*Припущення!$B$9 | M9: =K9/B9 | N9: =L9/B9 | O9: =IF(M9>=Припущення!$B$10,"ТАК","НІ")
A11: Нотатки:
A12: • ROAS (гейт) рахується на базі річного ARPPU — той самий базис, що й якір «~100% на 1-му місяці». Гейт = 125%.
A13: • M1 тримає витрати на $35K, але ріже переплату по бренду + сміттєві гео → CPI 0.666→0.560 → гейт пройдено ДО масштабування.
A14: • Базовий план дає 125% на самій CPT-ефективності (воронка фіксована). Приріст CR/Тріал→Оплата (CPP+PPO+пейвол) — це апсайд, не закладено.
A15: • «D30 ROAS» — довідковий: реальний кеш на D30 = ROAS × коеф. визнання (Припущення). Заміни 0.45 на реальну криву RevenueCat.

Sheet Чутливість
A1: Чутливість — який показник найбільше рухає ROAS?
A2: ROAS = (CR_тап→інстал × Тріал% × Оплата% × ARPPU) ÷ CPT. Ланцюг мультиплікативний → у кожного показника РІВНА % еластичність.
A4: Важіль | B4: База | C4: +10% покращення | D4: Новий ROAS | E4: Контроль / запас
A5: CR тап→інстал | B5: 0.42 | C5: =B5*1.1 | D5: +10% ROAS | E5: UA-керований через CPP / PPO — великий запас
A6: Тріал → Оплата | B6: 0.2 | C6: =B6*1.1 | D6: +10% ROAS | E6: Продукт/пейвол — найбільший запас, треба продукт
A7: Інстал → Тріал | B7: 0.15 | C7: =B7*1.1 | D7: +10% ROAS | E7: Онбординг — спільно з продуктом
A8: CPT (менше = краще) | B8: 0.238 | C8: =B8*0.9 | D8: +10% ROAS | E8: UA-керований через структуру/біди — найшвидший важіль
A10: Висновок: еластичність рівна, тож пріоритет за запасом × контрольованістю →
A11: 1) CPT-ефективність (задокументоване марнотратство — найшвидше), 2) Тріал→Оплата (лише 20%, найбільший запас), 3) tap→install CR через CPP/PPO.

Sheet Перерозподіл
A1: Поточний vs цільовий розподіл витрат ($35K)
A2: Перекидаю з бренд-переплати + сміттєвих мульти-гео → в ефективний US generic / competitor Search Results.
A4: Бакет | B4: Зараз % | C4: Зараз $ | D4: Ціль % | E4: Обґрунтування
A5: Бренд | B5: 0.58 | C5: =B5*35000 | D5: 0.25 | E5: Кап біда до ~факту; бренд частково канібалізує органіку. Звільняю бюджет.
A6: Generic Core (US, exact) | B6: 0.2 | C6: =B6*35000 | D6: 0.34 | E6: Масштабую перевірені head/mid-терміни під CPA-таргет.
A7: Generic Discovery (SM+Broad) | B7: 0.11 | C7: =B7*35000 | D7: 0.15 | E7: Ізольовано, негативи з Core; харвест переможців.
A8: Competitor (Search Results) | B8: 0.01 | C8: =B8*35000 | D8: 0.12 | E8: Новий conquesting у Search Results (був лише PP, CPA €17).
A9: Feature / мульти-гео T1 | B9: 0.1 | C9: =B9*35000 | D9: 0.14 | E9: Ріжу сміттєві гео; ізолюю US; feature у generic.
A10: РАЗОМ | B10: =SUM(B5:B9) | C10: =SUM(C5:C9) | D10: =SUM(D5:D9)
