Workbook

Sheet Assumptions
A1: TouchRetouch - ASA Funnel & ROAS Model
A2: Legend: orange = input you can change · blue = calculated. Revenue is modelled on first-year ARPPU (same basis as the ~100% anchor).
A4: CORE FUNNEL ASSUMPTIONS
A5: Metric | B5: Value | C5: Unit | D5: Note / source
A6: Install → Trial | B6: 0.15 | C6: % | D6: Given (paid funnel)
A7: Trial → Paid | B7: 0.2 | C7: % | D7: Given (paid funnel)
A8: ARPPU (Y1, net of Apple fee) | B8: 22.2 | C8: $ | D8: Given
A9: D30 revenue recognition (share of Y1) | B9: 0.45 | C9: % | D9: Info only (not in gate) - pull real D30/Y1 curve from RevenueCat
A10: Min ROAS gate for scaling (D30) | B10: 1.25 | C10: x | D10: Given requirement
A12: DERIVED UNIT ECONOMICS
A13: Payers per install | B13: =$B$6*$B$7 | D13: trial% × paid%
A14: Revenue per install (Y1) | B14: =$B$13*$B$8 | D14: payers/install × ARPPU
A15: Break-even CPI (ROAS 100%) | B15: =$B$14 | D15: equals revenue per install
A16: Target CPI for min ROAS | B16: =$B$14/$B$10 | D16: rev per install ÷ min ROAS
A18: KEY INSIGHT: the whole task = drop blended CPI to ≤ Target CPI and hold it while doubling spend.

Sheet Ramp Model
A1: Spend → Taps → Installs → Trials → Payers → Revenue → ROAS
A2: Orange cells drive the model. Everything else is a live formula. Plan: bank efficiency first (M1), then scale into the headroom.
A4: Phase / Month | B4: Spend ($) | C4: Blended CPT ($) | D4: TTR | E4: CR tap→install | F4: CPI ($) | G4: Taps | H4: Installs | I4: Trials | J4: Payers | K4: Revenue ($) | L4: D30 cash | M4: ROAS (gate) | N4: D30 ROAS | O4: Gate?
A5: M0 - Baseline (current) | B5: 35000 | C5: 0.2564 | D5: 0.07 | E5: 0.385 | F5: =C5/E5 | G5: =B5/C5 | H5: =G5*E5 | I5: =H5*Assumptions!$B$6 | J5: =I5*Assumptions!$B$7 | K5: =J5*Assumptions!$B$8 | L5: =K5*Assumptions!$B$9 | M5: =K5/B5 | N5: =L5/B5 | O5: =IF(M5>=Assumptions!$B$10,"YES","NO")
A6: M1 - Bank efficiency | B6: 35000 | C6: 0.224 | D6: 0.075 | E6: 0.4 | F6: =C6/E6 | G6: =B6/C6 | H6: =G6*E6 | I6: =H6*Assumptions!$B$6 | J6: =I6*Assumptions!$B$7 | K6: =J6*Assumptions!$B$8 | L6: =K6*Assumptions!$B$9 | M6: =K6/B6 | N6: =L6/B6 | O6: =IF(M6>=Assumptions!$B$10,"YES","NO")
A7: M2 - Gate cleared | B7: 40000 | C7: 0.223 | D7: 0.078 | E7: 0.42 | F7: =C7/E7 | G7: =B7/C7 | H7: =G7*E7 | I7: =H7*Assumptions!$B$6 | J7: =I7*Assumptions!$B$7 | K7: =J7*Assumptions!$B$8 | L7: =K7*Assumptions!$B$9 | M7: =K7/B7 | N7: =L7/B7 | O7: =IF(M7>=Assumptions!$B$10,"YES","NO")
A8: M3 - Scale above gate | B8: 55000 | C8: 0.2323 | D8: 0.08 | E8: 0.44 | F8: =C8/E8 | G8: =B8/C8 | H8: =G8*E8 | I8: =H8*Assumptions!$B$6 | J8: =I8*Assumptions!$B$7 | K8: =J8*Assumptions!$B$8 | L8: =K8*Assumptions!$B$9 | M8: =K8/B8 | N8: =L8/B8 | O8: =IF(M8>=Assumptions!$B$10,"YES","NO")
A9: Q2 - Target | B9: 70000 | C9: 0.2363 | D9: 0.082 | E9: 0.45 | F9: =C9/E9 | G9: =B9/C9 | H9: =G9*E9 | I9: =H9*Assumptions!$B$6 | J9: =I9*Assumptions!$B$7 | K9: =J9*Assumptions!$B$8 | L9: =K9*Assumptions!$B$9 | M9: =K9/B9 | N9: =L9/B9 | O9: =IF(M9>=Assumptions!$B$10,"YES","NO")
A11: Notes:
A12: • ROAS (gate) uses first-year ARPPU - same basis as the task's ~100% anchor. Gate = 125%.
A13: • M1 holds spend at $35K but caps brand bids + cuts junk geos → blended CPI 0.666→0.560 → gate cleared before scaling.
A14: • Base plan hits 125% on CPT efficiency alone; funnel gains (tool-CPP CR, paywall trial→paid) are upside, not baked in.
A15: • 'D30 cash ROAS' is informational: real cash by day 30 = ROAS × D30 recognition. Replace 0.45 with RevenueCat's real curve.

Sheet Sensitivity
A1: Sensitivity - which metric moves ROAS most?
A2: ROAS = (CR_tap→install × Trial% × Paid% × ARPPU) ÷ CPT. The chain is multiplicative → each metric has EQUAL % elasticity.
A4: Lever | B4: Baseline | C4: +10% improve | D4: New ROAS | E4: Controllability / headroom
A5: CR tap→install | B5: 0.42 | C5: =B5*1.1 | D5: +10% ROAS | E5: UA-owned via CPP/PPO - high headroom
A6: Trial → Paid | B6: 0.2 | C6: =B6*1.1 | D6: +10% ROAS | E6: Product/paywall - most headroom, needs product
A7: Install → Trial | B7: 0.15 | C7: =B7*1.1 | D7: +10% ROAS | E7: Onboarding - shared with product
A8: CPT (lower = better) | B8: 0.238 | C8: =B8*0.9 | D8: +10% ROAS | E8: UA-owned via structure/bids - fastest lever
A10: Conclusion: elasticity is equal → prioritise by headroom × controllability:
A11: 1) CPT efficiency (documented waste - fastest), 2) Trial→Paid (only 20%, most headroom), 3) tap→install CR via tool-CPPs/PPO.

Sheet Spend Reallocation
A1: Current vs target spend mix ($35K)
A2: Cap brand, kill competitor-on-Product-Pages, trim junk geos → redeploy into tool-intent CPP campaigns and the AI-positioning angle.
A4: Bucket | B4: Now % | C4: Now $ | D4: Target % | E4: Rationale
A5: Brand (capped + defensive) | B5: 0.58 | C5: =B5*35000 | D5: 0.15 | E5: Bid capped ~€3-5; brand is mostly cannibalised organic. Free budget.
A6: Generic Core (US, exact) | B6: 0.12 | C6: =B6*35000 | D6: 0.25 | E6: Proven head/mid terms (photo editor, object remover) under CPA target.
A7: Tool-intent CPP campaigns | B7: 0.1 | C7: =B7*35000 | D7: 0.33 | E7: Per-tool CPP ('magic eraser','object remover'…), aggressive bid per geo. Core money bucket.
A8: Search Match Discovery (isolated) | B8: 0.18 | C8: =B8*35000 | D8: 0.12 | E8: Isolated + Core as negatives; audit & harvest; kill non-converting terms.
A9: AI-positioning campaigns/CPP | B9: 0 | C9: =B9*35000 | D9: 0.08 | E9: New: capture users who'd otherwise ask ChatGPT/Gemini to edit a photo.
A10: Competitor (Search Results test) | B10: 0.01 | C10: =B10*35000 | D10: 0.05 | E10: Small conquest test in Search Results; Product-Pages competitor killed.
A11: Reserve / T1 geo expansion | B11: 0.01 | C11: =B11*35000 | D11: 0.02 | E11: Fund tested new T1 geos; junk geos (UZ/KG) removed.
A12: TOTAL | B12: =SUM(B5:B11) | C12: =SUM(C5:C11) | D12: =SUM(D5:D11)
